diffsim/__init__.py
diffsim/collision.py
diffsim/diff_physics.py
diffsim/diff_simulator.py
diffsim/material.py
diffsim/mesh.py
diffsim/simulator.py
diffsim/solver.py
diffsim/visualizer.py
torch_diffsim-0.1.0.dist-info/licenses/LICENSE
torch_diffsim-0.1.0.dist-info/METADATA
torch_diffsim-0.1.0.dist-info/WHEEL
torch_diffsim-0.1.0.dist-info/top_level.txt
torch_diffsim-0.1.0.dist-info/RECORD
