Metadata-Version: 2.4
Name: torch-diffsim
Version: 0.1.0
Summary: a very minimal paralllelizable physics simulator supporting differentiation entirely in torch.
Author-email: Rishit Dagli <rishit.dagli@gmail.com>
License: MIT
Project-URL: Homepage, https://github.com/Rishit-Dagli/torch-diffsim
Project-URL: Documentation, https://rishit-dagli.github.io/torch-diffsim/
Project-URL: Repository, https://github.com/Rishit-Dagli/torch-diffsim
Keywords: physics,simulation,differentiable,pytorch,neo-hookean
Classifier: Development Status :: 3 - Alpha
Classifier: Intended Audience :: Science/Research
Classifier: License :: OSI Approved :: MIT License
Classifier: Programming Language :: Python :: 3
Classifier: Programming Language :: Python :: 3.8
Classifier: Programming Language :: Python :: 3.9
Classifier: Programming Language :: Python :: 3.10
Classifier: Programming Language :: Python :: 3.11
Classifier: Programming Language :: Python :: 3.12
Classifier: Topic :: Scientific/Engineering :: Physics
Classifier: Topic :: Scientific/Engineering :: Artificial Intelligence
Requires-Python: >=3.8
License-File: LICENSE
Requires-Dist: torch>=2.0.0
Requires-Dist: numpy>=1.20.0
Requires-Dist: polyscope>=1.3.0
Requires-Dist: meshio>=5.0.0
Requires-Dist: scipy>=1.7.0
Requires-Dist: matplotlib>=3.5.0
Provides-Extra: dev
Requires-Dist: pytest>=7.0.0; extra == "dev"
Requires-Dist: black>=22.0.0; extra == "dev"
Requires-Dist: ruff>=0.1.0; extra == "dev"
Dynamic: license-file
